colour_splash/__init__.py
colour_splash/colour_splash.py
colour_splash-0.4.0.dist-info/LICENSE
colour_splash-0.4.0.dist-info/METADATA
colour_splash-0.4.0.dist-info/WHEEL
colour_splash-0.4.0.dist-info/top_level.txt
colour_splash-0.4.0.dist-info/RECORD
