Metadata-Version: 2.1
Name: colour-splash
Version: 0.4.0
Summary: A simple tool enabling easy colouring of terminal outputs
Author: Lachlan Rehder
Author-email: lachlan2357@outlook.com
License: GPLv3
Project-URL: Homepage, https://github.com/lachlan2357/python-colour-splash
Project-URL: Changelog, https://github.com/lachlan2357/python-colour-splash/blob/main/CHANGELOG.md
Project-URL: Bug Tracker, https://github.com/lachlan2357/python-colour-splash/issues
Project-URL: Source, https://github.com/lachlan2357/python-colour-splash
Classifier: Programming Language :: Python :: 3
Classifier: License :: OSI Approved :: GNU General Public License v3 (GPLv3)
Classifier: Operating System :: OS Independent
Classifier: Development Status :: 4 - Beta
Requires-Python: >=3.7
License-File: LICENSE
